{
  "_id": "energy-leg0006",
  "name": "Level 06",
  "type": "critical-effect",
  "img": "systems/deathwatch/icons/tables/critical-damage.webp",
  "system": {
    "book": "Deathwatch Core Rulebook",
    "page": "253",
    "damageType": "Energy",
    "location": "Leg",
    "description": "The attack burns the target's foot, charring the flesh and emitting a foul aroma. The target must successfully Test Toughness or lose the foot. On a success, the target's movement rates are halved until he receives medical attention. In addition, the target takes 2 levels of Fatigue.",
    "effects": []
  }
}
