{
  "_id": "impact-body0007",
  "name": "Level 07",
  "type": "critical-effect",
  "img": "systems/deathwatch/icons/tables/critical-damage.webp",
  "system": {
    "damageType": "Impact",
    "location": "Body",
    "description": "With an audible crack, 1d5 of the target's ribs break. The target can either lay down and stay still awaiting medical attention (a successful Medicae Test sets the ribs) or continue to take Actions, though each Round there is a 20% chance that a jagged rib pierces a vital organ and kills the character instantly. The target takes 1d5 levels of Fatigue.",
    "effects": []
  }
}
